PyShapes/PyShape.py
PyShapes/__init__.py
PyShapes-1.1.4.dist-info/LICENSE
PyShapes-1.1.4.dist-info/METADATA
PyShapes-1.1.4.dist-info/WHEEL
PyShapes-1.1.4.dist-info/top_level.txt
PyShapes-1.1.4.dist-info/RECORD
