Metadata-Version: 2.1
Name: PyShapes
Version: 1.1.4
Summary: A shape detection module for Python
Home-page: https://github.com/sudoRicheek/PyShapes
Author: Richeek Das
Author-email: richeekdas2001@gmail.com
License: UNKNOWN
Platform: UNKNOWN
Classifier: Programming Language :: Python :: 3.5
Classifier: Programming Language :: Python :: 3.6
Classifier: Programming Language :: Python :: 3.7
Classifier: License :: OSI Approved :: MIT License
Classifier: Operating System :: OS Independent
Requires-Python: >=3.5
